nitroml/__init__.py
nitroml-0.0.0.dev1.dist-info/LICENSE
nitroml-0.0.0.dev1.dist-info/METADATA
nitroml-0.0.0.dev1.dist-info/WHEEL
nitroml-0.0.0.dev1.dist-info/top_level.txt
nitroml-0.0.0.dev1.dist-info/RECORD
